dutchsoils/__init__.py
dutchsoils/data/BofekClusters.csv
dutchsoils/data/BofekClustersNames.csv
dutchsoils/data/SoilHorizons.csv
dutchsoils/data/SoilProfiles.csv
dutchsoils/data/soilprofiles_BodemkaartBofek.csv
dutchsoils/data/Staringreeks2018.csv
dutchsoils/data/StaringreeksNamen2018.csv
dutchsoils/plot.py
dutchsoils/soilprofile.py
dutchsoils-0.3.1.dist-info/LICENSE
dutchsoils-0.3.1.dist-info/METADATA
dutchsoils-0.3.1.dist-info/WHEEL
dutchsoils-0.3.1.dist-info/RECORD
