Metadata-Version: 2.3
Name: dutchsoils
Version: 0.3.1
Summary: Package to get soil profiles of the Netherlands.
License: MIT
Author: markvdbrink
Author-email: mark.vandenbrink@wur.nl
Maintainer: markvdbrink
Maintainer-email: mark.vandenbrink@wur.nl
Requires-Python: >=3.11
Classifier: Development Status :: 4 - Beta
Classifier: Intended Audience :: Science/Research
Classifier: Intended Audience :: Other Audience
Classifier: License :: OSI Approved :: MIT License
Classifier: Programming Language :: Python :: 3 :: Only
Classifier: Programming Language :: Python :: 3.11
Classifier: Programming Language :: Python :: 3.12
Classifier: Programming Language :: Python :: 3.13
Classifier: Topic :: Scientific/Engineering :: Hydrology
Classifier: Operating System :: OS Independent
Provides-Extra: dev
Provides-Extra: ipykernel
Requires-Dist: coverage (>=7.10,<8.0) ; extra == "dev"
Requires-Dist: ipykernel (>=6.29,<7.0) ; extra == "ipykernel"
Requires-Dist: matplotlib (>=3.10)
Requires-Dist: myst-nb (>=1.3,<2.0) ; extra == "dev"
Requires-Dist: myst-parser (>=4.0) ; extra == "dev"
Requires-Dist: numpy (>=1.26)
Requires-Dist: numpydoc (>=1.9,<2.0) ; extra == "dev"
Requires-Dist: pandas (>=2.2)
Requires-Dist: pedon (>=0.0)
Requires-Dist: pre-commit (>=4.2,<5.0) ; extra == "dev"
Requires-Dist: pydata-sphinx-theme (>=0.16,<1.0) ; extra == "dev"
Requires-Dist: pyproj (>=3.7.1)
Requires-Dist: pytest (>=8.4,<9.0) ; extra == "dev"
Requires-Dist: requests (>=2.32.4)
Requires-Dist: sphinx (>=8.2,<9.0) ; extra == "dev"
Project-URL: Homepage, https://github.com/markvdbrink/dutchsoils
Project-URL: Issues, https://github.com/markvdbrink/dutchsoils/issues
Project-URL: Source, https://bodemdata.nl/basiskaarten
